{
  "version": "5",
  "dialect": "pg",
  "entries": [
    {
      "idx": 0,
      "version": "5",
      "when": 1705685810664,
      "tag": "0000_third_turbo",
      "breakpoints": true
    },
    {
      "idx": 1,
      "version": "5",
      "when": 1706580028287,
      "tag": "0001_perpetual_psynapse",
      "breakpoints": true
    },
    {
      "idx": 2,
      "version": "5",
      "when": 1706731243037,
      "tag": "0002_shallow_loa",
      "breakpoints": true
    },
    {
      "idx": 3,
      "version": "5",
      "when": 1706809890667,
      "tag": "0003_peaceful_killraven",
      "breakpoints": true
    },
    {
      "idx": 4,
      "version": "5",
      "when": 1706815765791,
      "tag": "0004_smooth_preak",
      "breakpoints": true
    },
    {
      "idx": 5,
      "version": "5",
      "when": 1706916522622,
      "tag": "0005_friendly_wind_dancer",
      "breakpoints": true
    },
    {
      "idx": 6,
      "version": "5",
      "when": 1706969803889,
      "tag": "0006_flippant_cobalt_man",
      "breakpoints": true
    },
    {
      "idx": 7,
      "version": "5",
      "when": 1707103066482,
      "tag": "0007_chubby_scarlet_spider",
      "breakpoints": true
    },
    {
      "idx": 8,
      "version": "5",
      "when": 1707194635538,
      "tag": "0008_certain_juggernaut",
      "breakpoints": true
    },
    {
      "idx": 9,
      "version": "5",
      "when": 1707792666051,
      "tag": "0009_modern_nico_minoru",
      "breakpoints": true
    },
    {
      "idx": 10,
      "version": "5",
      "when": 1707951512171,
      "tag": "0010_striped_lila_cheney",
      "breakpoints": true
    },
    {
      "idx": 11,
      "version": "5",
      "when": 1707952395884,
      "tag": "0011_tiny_miracleman",
      "breakpoints": true
    },
    {
      "idx": 12,
      "version": "5",
      "when": 1708009560566,
      "tag": "0012_glossy_tusk",
      "breakpoints": true
    },
    {
      "idx": 13,
      "version": "5",
      "when": 1708024091099,
      "tag": "0013_spotty_jocasta",
      "breakpoints": true
    },
    {
      "idx": 14,
      "version": "5",
      "when": 1708024476268,
      "tag": "0014_warm_darkhawk",
      "breakpoints": true
    },
    {
      "idx": 15,
      "version": "5",
      "when": 1708024779754,
      "tag": "0015_breezy_dust",
      "breakpoints": true
    },
    {
      "idx": 16,
      "version": "5",
      "when": 1709071185184,
      "tag": "0016_parched_otto_octavius",
      "breakpoints": true
    },
    {
      "idx": 17,
      "version": "5",
      "when": 1709588304086,
      "tag": "0017_fantastic_robbie_robertson",
      "breakpoints": true
    },
    {
      "idx": 18,
      "version": "5",
      "when": 1709741317451,
      "tag": "0018_first_bucky",
      "breakpoints": true
    },
    {
      "idx": 19,
      "version": "5",
      "when": 1710276189271,
      "tag": "0019_concerned_scarecrow",
      "breakpoints": true
    },
    {
      "idx": 20,
      "version": "5",
      "when": 1710520035239,
      "tag": "0020_first_praxagora",
      "breakpoints": true
    },
    {
      "idx": 21,
      "version": "5",
      "when": 1710533672651,
      "tag": "0021_dapper_sunfire",
      "breakpoints": true
    },
    {
      "idx": 22,
      "version": "5",
      "when": 1710795634535,
      "tag": "0022_lowly_iron_monger",
      "breakpoints": true
    },
    {
      "idx": 23,
      "version": "5",
      "when": 1710955342805,
      "tag": "0023_wise_alice",
      "breakpoints": true
    },
    {
      "idx": 24,
      "version": "5",
      "when": 1710958464058,
      "tag": "0024_naive_beast",
      "breakpoints": true
    },
    {
      "idx": 25,
      "version": "5",
      "when": 1711392051313,
      "tag": "0025_confused_the_santerians",
      "breakpoints": true
    },
    {
      "idx": 26,
      "version": "5",
      "when": 1711416193412,
      "tag": "0026_icy_iron_lad",
      "breakpoints": true
    },
    {
      "idx": 27,
      "version": "5",
      "when": 1711664260689,
      "tag": "0027_hot_retro_girl",
      "breakpoints": true
    },
    {
      "idx": 28,
      "version": "5",
      "when": 1711739810145,
      "tag": "0028_foamy_microchip",
      "breakpoints": true
    },
    {
      "idx": 29,
      "version": "5",
      "when": 1711985633460,
      "tag": "0029_deep_sir_ram",
      "breakpoints": true
    },
    {
      "idx": 30,
      "version": "5",
      "when": 1711990905512,
      "tag": "0030_wide_bromley",
      "breakpoints": true
    },
    {
      "idx": 31,
      "version": "5",
      "when": 1712193251767,
      "tag": "0031_nervous_veda",
      "breakpoints": true
    },
    {
      "idx": 32,
      "version": "5",
      "when": 1712194930275,
      "tag": "0032_lucky_tempest",
      "breakpoints": true
    },
    {
      "idx": 33,
      "version": "5",
      "when": 1713370036581,
      "tag": "0033_pretty_skreet",
      "breakpoints": true
    },
    {
      "idx": 34,
      "version": "5",
      "when": 1713385048447,
      "tag": "0034_amazing_tiger_shark",
      "breakpoints": true
    },
    {
      "idx": 35,
      "version": "5",
      "when": 1713708562930,
      "tag": "0035_empty_mordo",
      "breakpoints": true
    },
    {
      "idx": 36,
      "version": "5",
      "when": 1713818662077,
      "tag": "0036_solid_goliath",
      "breakpoints": true
    },
    {
      "idx": 37,
      "version": "5",
      "when": 1714786844578,
      "tag": "0037_great_longshot",
      "breakpoints": true
    },
    {
      "idx": 38,
      "version": "5",
      "when": 1714827806956,
      "tag": "0038_tan_hiroim",
      "breakpoints": true
    },
    {
      "idx": 39,
      "version": "5",
      "when": 1715016818346,
      "tag": "0039_powerful_mandroid",
      "breakpoints": true
    },
    {
      "idx": 40,
      "version": "5",
      "when": 1715804689503,
      "tag": "0040_empty_bruce_banner",
      "breakpoints": true
    },
    {
      "idx": 41,
      "version": "6",
      "when": 1716222832084,
      "tag": "0041_optimal_black_knight",
      "breakpoints": true
    },
    {
      "idx": 42,
      "version": "7",
      "when": 1717440494321,
      "tag": "0042_yielding_stryfe",
      "breakpoints": true
    },
    {
      "idx": 43,
      "version": "7",
      "when": 1717600620100,
      "tag": "0043_plain_beyonder",
      "breakpoints": true
    },
    {
      "idx": 44,
      "version": "7",
      "when": 1717610290532,
      "tag": "0044_careless_longshot",
      "breakpoints": true
    },
    {
      "idx": 45,
      "version": "7",
      "when": 1717689244642,
      "tag": "0045_loud_black_bird",
      "breakpoints": true
    },
    {
      "idx": 46,
      "version": "7",
      "when": 1718125975097,
      "tag": "0046_premium_newton_destine",
      "breakpoints": true
    },
    {
      "idx": 47,
      "version": "7",
      "when": 1719000234715,
      "tag": "0047_sticky_morbius",
      "breakpoints": true
    },
    {
      "idx": 48,
      "version": "7",
      "when": 1719429489397,
      "tag": "0048_illegal_betty_ross",
      "breakpoints": true
    },
    {
      "idx": 49,
      "version": "7",
      "when": 1719431802482,
      "tag": "0049_silly_blink",
      "breakpoints": true
    },
    {
      "idx": 50,
      "version": "7",
      "when": 1721065826224,
      "tag": "0050_fluffy_puck",
      "breakpoints": true
    },
    {
      "idx": 51,
      "version": "7",
      "when": 1722349340724,
      "tag": "0051_eager_tenebrous",
      "breakpoints": true
    },
    {
      "idx": 52,
      "version": "7",
      "when": 1722351836889,
      "tag": "0052_watery_charles_xavier",
      "breakpoints": true
    },
    {
      "idx": 53,
      "version": "7",
      "when": 1722453060606,
      "tag": "0053_dapper_skullbuster",
      "breakpoints": true
    },
    {
      "idx": 54,
      "version": "7",
      "when": 1724434170575,
      "tag": "0054_giant_maggott",
      "breakpoints": true
    },
    {
      "idx": 55,
      "version": "7",
      "when": 1724445346373,
      "tag": "0055_productive_mesmero",
      "breakpoints": true
    },
    {
      "idx": 56,
      "version": "7",
      "when": 1724682408553,
      "tag": "0056_round_galactus",
      "breakpoints": true
    },
    {
      "idx": 57,
      "version": "7",
      "when": 1725402051432,
      "tag": "0057_stale_rogue",
      "breakpoints": true
    },
    {
      "idx": 58,
      "version": "7",
      "when": 1725402441849,
      "tag": "0058_left_secret_warriors",
      "breakpoints": true
    },
    {
      "idx": 59,
      "version": "7",
      "when": 1725562212544,
      "tag": "0059_gorgeous_vector",
      "breakpoints": true
    },
    {
      "idx": 60,
      "version": "7",
      "when": 1726154954306,
      "tag": "0060_clever_wildside",
      "breakpoints": true
    },
    {
      "idx": 61,
      "version": "7",
      "when": 1726695886128,
      "tag": "0061_wide_bruce_banner",
      "breakpoints": true
    },
    {
      "idx": 62,
      "version": "7",
      "when": 1726717373761,
      "tag": "0062_serious_xavin",
      "breakpoints": true
    },
    {
      "idx": 63,
      "version": "7",
      "when": 1726759713563,
      "tag": "0063_glamorous_captain_midlands",
      "breakpoints": true
    },
    {
      "idx": 64,
      "version": "7",
      "when": 1726851219453,
      "tag": "0064_curved_hulk",
      "breakpoints": true
    },
    {
      "idx": 65,
      "version": "7",
      "when": 1727294631631,
      "tag": "0065_bumpy_magus",
      "breakpoints": true
    },
    {
      "idx": 66,
      "version": "7",
      "when": 1728402823549,
      "tag": "0066_dusty_earthquake",
      "breakpoints": true
    },
    {
      "idx": 67,
      "version": "7",
      "when": 1729191573168,
      "tag": "0067_strange_lifeguard",
      "breakpoints": true
    },
    {
      "idx": 68,
      "version": "7",
      "when": 1731434691066,
      "tag": "0068_panoramic_sugar_man",
      "breakpoints": true
    },
    {
      "idx": 69,
      "version": "7",
      "when": 1731969306208,
      "tag": "0069_tiny_triathlon",
      "breakpoints": true
    },
    {
      "idx": 70,
      "version": "7",
      "when": 1733181888609,
      "tag": "0070_abnormal_nightmare",
      "breakpoints": true
    },
    {
      "idx": 71,
      "version": "7",
      "when": 1733255272208,
      "tag": "0071_glamorous_wild_pack",
      "breakpoints": true
    },
    {
      "idx": 72,
      "version": "7",
      "when": 1733424131456,
      "tag": "0072_rainy_zaladane",
      "breakpoints": true
    },
    {
      "idx": 73,
      "version": "7",
      "when": 1733527002274,
      "tag": "0073_rare_korvac",
      "breakpoints": true
    },
    {
      "idx": 74,
      "version": "7",
      "when": 1734362826779,
      "tag": "0074_eminent_stick",
      "breakpoints": true
    },
    {
      "idx": 75,
      "version": "7",
      "when": 1734485752848,
      "tag": "0075_clumsy_alex_power",
      "breakpoints": true
    },
    {
      "idx": 76,
      "version": "7",
      "when": 1734727961068,
      "tag": "0076_messy_swordsman",
      "breakpoints": true
    },
    {
      "idx": 77,
      "version": "7",
      "when": 1734885033661,
      "tag": "0077_cloudy_expediter",
      "breakpoints": true
    },
    {
      "idx": 78,
      "version": "7",
      "when": 1734989247320,
      "tag": "0078_mixed_deathbird",
      "breakpoints": true
    },
    {
      "idx": 79,
      "version": "7",
      "when": 1735237234267,
      "tag": "0079_dizzy_hawkeye",
      "breakpoints": true
    },
    {
      "idx": 80,
      "version": "7",
      "when": 1735323219376,
      "tag": "0080_demonic_wither",
      "breakpoints": true
    },
    {
      "idx": 81,
      "version": "7",
      "when": 1735613720206,
      "tag": "0081_fluffy_loners",
      "breakpoints": true
    },
    {
      "idx": 82,
      "version": "7",
      "when": 1736129468932,
      "tag": "0082_flat_whizzer",
      "breakpoints": true
    },
    {
      "idx": 83,
      "version": "7",
      "when": 1736132332081,
      "tag": "0083_glorious_ken_ellis",
      "breakpoints": true
    },
    {
      "idx": 84,
      "version": "7",
      "when": 1736994788279,
      "tag": "0084_clumsy_betty_brant",
      "breakpoints": true
    },
    {
      "idx": 85,
      "version": "7",
      "when": 1737570878443,
      "tag": "0085_parched_celestials",
      "breakpoints": true
    },
    {
      "idx": 86,
      "version": "7",
      "when": 1738170297346,
      "tag": "0086_fixed_thunderball",
      "breakpoints": true
    },
    {
      "idx": 87,
      "version": "7",
      "when": 1738170479655,
      "tag": "0087_lean_bruce_banner",
      "breakpoints": true
    },
    {
      "idx": 88,
      "version": "7",
      "when": 1738266453604,
      "tag": "0088_moaning_skreet",
      "breakpoints": true
    },
    {
      "idx": 89,
      "version": "7",
      "when": 1738278981225,
      "tag": "0089_wise_fallen_one",
      "breakpoints": true
    },
    {
      "idx": 90,
      "version": "7",
      "when": 1738292998153,
      "tag": "0090_nosy_thunderbolts",
      "breakpoints": true
    },
    {
      "idx": 91,
      "version": "7",
      "when": 1738343483207,
      "tag": "0091_clammy_prodigy",
      "breakpoints": true
    },
    {
      "idx": 92,
      "version": "7",
      "when": 1738724273479,
      "tag": "0092_late_toad_men",
      "breakpoints": true
    },
    {
      "idx": 93,
      "version": "7",
      "when": 1742487900663,
      "tag": "0093_wild_spectrum",
      "breakpoints": true
    },
    {
      "idx": 94,
      "version": "7",
      "when": 1742493516316,
      "tag": "0094_striped_maginty",
      "breakpoints": true
    },
    {
      "idx": 95,
      "version": "7",
      "when": 1743021753034,
      "tag": "0095_silent_electro",
      "breakpoints": true
    },
    {
      "idx": 96,
      "version": "7",
      "when": 1743216940327,
      "tag": "0096_moaning_dexter_bennett",
      "breakpoints": true
    },
    {
      "idx": 97,
      "version": "7",
      "when": 1743525375344,
      "tag": "0097_amusing_angel",
      "breakpoints": true
    },
    {
      "idx": 98,
      "version": "7",
      "when": 1743609633456,
      "tag": "0098_careless_forgotten_one",
      "breakpoints": true
    },
    {
      "idx": 99,
      "version": "7",
      "when": 1744236815234,
      "tag": "0099_loud_bucky",
      "breakpoints": true
    },
    {
      "idx": 100,
      "version": "7",
      "when": 1745346810851,
      "tag": "0100_real_union_jack",
      "breakpoints": true
    },
    {
      "idx": 101,
      "version": "7",
      "when": 1745347157473,
      "tag": "0101_luxuriant_ego",
      "breakpoints": true
    },
    {
      "idx": 102,
      "version": "7",
      "when": 1745347317761,
      "tag": "0102_medical_the_captain",
      "breakpoints": true
    },
    {
      "idx": 103,
      "version": "7",
      "when": 1747756555248,
      "tag": "0103_amused_shiva",
      "breakpoints": true
    },
    {
      "idx": 104,
      "version": "7",
      "when": 1747880667566,
      "tag": "0104_next_vapor",
      "breakpoints": true
    },
    {
      "idx": 105,
      "version": "7",
      "when": 1747939864088,
      "tag": "0105_mean_agent_brand",
      "breakpoints": true
    },
    {
      "idx": 106,
      "version": "7",
      "when": 1749064804962,
      "tag": "0106_needy_mindworm",
      "breakpoints": true
    },
    {
      "idx": 107,
      "version": "7",
      "when": 1749584080332,
      "tag": "0107_true_red_ghost",
      "breakpoints": true
    },
    {
      "idx": 108,
      "version": "7",
      "when": 1749763453855,
      "tag": "0108_living_warbound",
      "breakpoints": true
    },
    {
      "idx": 109,
      "version": "7",
      "when": 1750099477205,
      "tag": "0109_graceful_shotgun",
      "breakpoints": true
    },
    {
      "idx": 110,
      "version": "7",
      "when": 1750194702441,
      "tag": "0110_silly_micromax",
      "breakpoints": true
    },
    {
      "idx": 111,
      "version": "7",
      "when": 1750443329463,
      "tag": "0111_bored_texas_twister",
      "breakpoints": true
    },
    {
      "idx": 112,
      "version": "7",
      "when": 1750515610378,
      "tag": "0112_clear_gladiator",
      "breakpoints": true
    },
    {
      "idx": 113,
      "version": "7",
      "when": 1752006449645,
      "tag": "0113_far_avengers",
      "breakpoints": true
    },
    {
      "idx": 114,
      "version": "7",
      "when": 1752099723058,
      "tag": "0114_fair_marauders",
      "breakpoints": true
    },
    {
      "idx": 115,
      "version": "7",
      "when": 1754749866877,
      "tag": "0115_hesitant_sway",
      "breakpoints": true
    },
    {
      "idx": 116,
      "version": "7",
      "when": 1754752003923,
      "tag": "0116_exotic_blindfold",
      "breakpoints": true
    },
    {
      "idx": 117,
      "version": "7",
      "when": 1754762719464,
      "tag": "0117_military_lila_cheney",
      "breakpoints": true
    },
    {
      "idx": 118,
      "version": "7",
      "when": 1755113376149,
      "tag": "0118_overjoyed_mephisto",
      "breakpoints": true
    },
    {
      "idx": 119,
      "version": "7",
      "when": 1755122064107,
      "tag": "0119_superb_daimon_hellstrom",
      "breakpoints": true
    },
    {
      "idx": 120,
      "version": "7",
      "when": 1755523455423,
      "tag": "0120_wonderful_jean_grey",
      "breakpoints": true
    },
    {
      "idx": 121,
      "version": "7",
      "when": 1755542622774,
      "tag": "0121_round_charles_xavier",
      "breakpoints": true
    },
    {
      "idx": 122,
      "version": "7",
      "when": 1756165886580,
      "tag": "0122_tiny_silvermane",
      "breakpoints": true
    },
    {
      "idx": 123,
      "version": "7",
      "when": 1756738590883,
      "tag": "0123_far_cassandra_nova",
      "breakpoints": true
    },
    {
      "idx": 124,
      "version": "7",
      "when": 1756916307674,
      "tag": "0124_sturdy_true_believers",
      "breakpoints": true
    },
    {
      "idx": 125,
      "version": "7",
      "when": 1756926005502,
      "tag": "0125_huge_cardiac",
      "breakpoints": true
    },
    {
      "idx": 126,
      "version": "7",
      "when": 1759274232725,
      "tag": "0126_glamorous_sasquatch",
      "breakpoints": true
    },
    {
      "idx": 127,
      "version": "7",
      "when": 1759513627767,
      "tag": "0127_dashing_blackheart",
      "breakpoints": true
    },
    {
      "idx": 128,
      "version": "7",
      "when": 1759954974243,
      "tag": "0128_easy_iron_fist",
      "breakpoints": true
    },
    {
      "idx": 129,
      "version": "7",
      "when": 1760058045770,
      "tag": "0129_brave_blacklash",
      "breakpoints": true
    },
    {
      "idx": 130,
      "version": "7",
      "when": 1760059210971,
      "tag": "0130_windy_vertigo",
      "breakpoints": true
    },
    {
      "idx": 131,
      "version": "7",
      "when": 1760477857277,
      "tag": "0131_workable_naoko",
      "breakpoints": true
    },
    {
      "idx": 132,
      "version": "7",
      "when": 1760884810274,
      "tag": "0132_public_reptil",
      "breakpoints": true
    },
    {
      "idx": 133,
      "version": "7",
      "when": 1761682954761,
      "tag": "0133_wild_talon",
      "breakpoints": true
    },
    {
      "idx": 134,
      "version": "7",
      "when": 1761683682912,
      "tag": "0134_fast_wendell_vaughn",
      "breakpoints": true
    },
    {
      "idx": 135,
      "version": "7",
      "when": 1762198551062,
      "tag": "0135_cold_colonel_america",
      "breakpoints": true
    },
    {
      "idx": 136,
      "version": "7",
      "when": 1764167125391,
      "tag": "0136_natural_prowler",
      "breakpoints": true
    },
    {
      "idx": 137,
      "version": "7",
      "when": 1764544176401,
      "tag": "0137_fixed_quasimodo",
      "breakpoints": true
    }
  ]
}